PlaywrightSafeThread/__init__.py
PlaywrightSafeThread/browser/__init__.py
PlaywrightSafeThread/browser/plawright_shim.py
PlaywrightSafeThread/browser/threadsafe_browser.py
PlaywrightSafeThread-0.5.5.dist-info/LICENSE
PlaywrightSafeThread-0.5.5.dist-info/METADATA
PlaywrightSafeThread-0.5.5.dist-info/WHEEL
PlaywrightSafeThread-0.5.5.dist-info/top_level.txt
PlaywrightSafeThread-0.5.5.dist-info/RECORD
