Metadata-Version: 2.1
Name: PlaywrightSafeThread
Version: 0.5.5
Summary: PlaywrightSafeThread
Home-page: https://github.com/3mora2/PlaywrightSafeThread
Author: Ammar Alkotb
Author-email: ammar.alkotb@gmail.com
License: MIT License
Project-URL: Bug Report, https://github.com/3mora2/PlaywrightSafeThread/issues/new
Classifier: License :: OSI Approved :: MIT License
Classifier: Intended Audience :: Developers
Classifier: Programming Language :: Python
Classifier: Topic :: Software Development :: Libraries :: Python Modules
License-File: LICENSE
Requires-Dist: playwright
Requires-Dist: playwright-stealth
Requires-Dist: psutil
